parliamentarch/__init__.py
parliamentarch/__main__.py
parliamentarch/_util.py
parliamentarch/geometry.py
parliamentarch/svg.py
ParliamentArch-1.1.2.dist-info/LICENSE
ParliamentArch-1.1.2.dist-info/METADATA
ParliamentArch-1.1.2.dist-info/WHEEL
ParliamentArch-1.1.2.dist-info/top_level.txt
ParliamentArch-1.1.2.dist-info/RECORD
