Metadata-Version: 2.1
Name: ParliamentArch
Version: 1.1.2
Summary: Generation of arch-styled parliamentary arches
Author: Gouvernathor
License: BSD 3-Clause License
Project-URL: Repository, https://github.com/Gouvernathor/parliamentarch
Requires-Python: >=3.11
License-File: LICENSE
